nuql/__init__.py
nuql/client.py
nuql/connection.py
nuql/exceptions.py
nuql/api/__init__.py
nuql/api/adapter.py
nuql/api/batch_write.py
nuql/api/condition_check.py
nuql/api/create.py
nuql/api/delete.py
nuql/api/get.py
nuql/api/put_item.py
nuql/api/put_update.py
nuql/api/transaction.py
nuql/api/upsert.py
nuql/api/batch_get/__init__.py
nuql/api/batch_get/batch_get.py
nuql/api/batch_get/queue.py
nuql/api/query/__init__.py
nuql/api/query/condition.py
nuql/api/query/condition_builder.py
nuql/api/query/key_condition.py
nuql/api/query/query.py
nuql/api/update/__init__.py
nuql/api/update/expression_builder.py
nuql/api/update/update_item.py
nuql/api/update/utils.py
nuql/fields/__init__.py
nuql/fields/boolean.py
nuql/fields/datetime.py
nuql/fields/datetime_timestamp.py
nuql/fields/float.py
nuql/fields/integer.py
nuql/fields/key.py
nuql/fields/list.py
nuql/fields/map.py
nuql/fields/string.py
nuql/fields/ulid.py
nuql/fields/uuid.py
nuql/generators/__init__.py
nuql/generators/datetime.py
nuql/generators/ulid.py
nuql/generators/uuid.py
nuql/resources/__init__.py
nuql/resources/fields/__init__.py
nuql/resources/fields/field.py
nuql/resources/fields/field_map.py
nuql/resources/fields/value.py
nuql/resources/records/__init__.py
nuql/resources/records/projections.py
nuql/resources/records/serialiser.py
nuql/resources/records/validator.py
nuql/resources/tables/__init__.py
nuql/resources/tables/indexes.py
nuql/resources/tables/table.py
nuql/resources/utils/__init__.py
nuql/resources/utils/dict.py
nuql/resources/utils/validators.py
nuql/types/__init__.py
nuql/types/config.py
nuql/types/fields.py
nuql/types/serialisation.py
nuql-0.0.21.dist-info/METADATA
nuql-0.0.21.dist-info/WHEEL
nuql-0.0.21.dist-info/licenses/LICENSE
nuql-0.0.21.dist-info/RECORD
